xoa_driver/__init__.py
xoa_driver/enums.py
xoa_driver/exceptions.py
xoa_driver/hlfuncs.py
xoa_driver/lli.py
xoa_driver/misc.py
xoa_driver/modules.py
xoa_driver/ports.py
xoa_driver/testers.py
xoa_driver/utils.py
xoa_driver/functions/__init__.py
xoa_driver/functions/anlt.py
xoa_driver/functions/anlt_ll_debug.py
xoa_driver/functions/cli.py
xoa_driver/functions/exceptions.py
xoa_driver/functions/headers.py
xoa_driver/functions/mgmt.py
xoa_driver/functions/tools.py
xoa_driver/internals/__init__.py
xoa_driver/internals/warn.py
xoa_driver/internals/commands/__init__.py
xoa_driver/internals/commands/c_commands.py
xoa_driver/internals/commands/enums.py
xoa_driver/internals/commands/m4_commands.py
xoa_driver/internals/commands/m4e_commands.py
xoa_driver/internals/commands/m_commands.py
xoa_driver/internals/commands/p4_commands.py
xoa_driver/internals/commands/p4e_commands.py
xoa_driver/internals/commands/p4g_commands.py
xoa_driver/internals/commands/p_commands.py
xoa_driver/internals/commands/pc_commands.py
xoa_driver/internals/commands/pd_commands.py
xoa_driver/internals/commands/pe_commands.py
xoa_driver/internals/commands/pec_commands.py
xoa_driver/internals/commands/ped_commands.py
xoa_driver/internals/commands/pef_commands.py
xoa_driver/internals/commands/pf_commands.py
xoa_driver/internals/commands/pl1_commands.py
xoa_driver/internals/commands/pl_commands.py
xoa_driver/internals/commands/pm_commands.py
xoa_driver/internals/commands/pp_commands.py
xoa_driver/internals/commands/pr_commands.py
xoa_driver/internals/commands/ps_commands.py
xoa_driver/internals/commands/pt_commands.py
xoa_driver/internals/commands/px_commands.py
xoa_driver/internals/commands/subtypes.py
xoa_driver/internals/core/__init__.py
xoa_driver/internals/core/builders.py
xoa_driver/internals/core/exceptions.py
xoa_driver/internals/core/funcs.py
xoa_driver/internals/core/funcs.pyi
xoa_driver/internals/core/interfaces.py
xoa_driver/internals/core/token.py
xoa_driver-2.9.3.dist-info/LICENSE
xoa_driver-2.9.3.dist-info/METADATA
xoa_driver-2.9.3.dist-info/WHEEL
xoa_driver-2.9.3.dist-info/top_level.txt
xoa_driver-2.9.3.dist-info/RECORD
