Metadata-Version: 2.2
Name: xoa-driver
Version: 2.9.3
Summary: Xena OpenAutomation (XOA) Python API is a driver providing user-friendly communication interfaces to Xena's physical and virtual Traffic Generation and Analysis (TGA) testers. It provides a rich collection of programming interfaces that can be used to either write test scripts or develop applications.
Home-page: https://github.com/xenanetworks/open-automation-python-api
Author: Artem Constantinov, Ron Ding, Leonard Yu
Author-email: leonard.yu@teledyne.com
Maintainer: Teledyne LeCroy Xena
Maintainer-email: support@xenanetworks.com
License: Apache 2.0
Classifier: Development Status :: 5 - Production/Stable
Classifier: Intended Audience :: Developers
Classifier: Topic :: Software Development :: Libraries :: Python Modules
Classifier: License :: OSI Approved :: Apache Software License
Classifier: Programming Language :: Python :: 3.8
Classifier: Programming Language :: Python :: 3.9
Classifier: Programming Language :: Python :: 3.10
Classifier: Programming Language :: Python :: 3.11
Requires-Python: >=3.8
License-File: LICENSE
Requires-Dist: typing_extensions
Dynamic: author
Dynamic: author-email
Dynamic: classifier
Dynamic: description
Dynamic: description-content-type
Dynamic: home-page
Dynamic: license
Dynamic: maintainer
Dynamic: maintainer-email
Dynamic: requires-dist
Dynamic: requires-python
Dynamic: summary
